sphinx_pythia_theme/__init__.py
sphinx_pythia_theme/banner.py
sphinx_pythia_theme/footer-extra.html
sphinx_pythia_theme/footer-info.html
sphinx_pythia_theme/footer-logos.html
sphinx_pythia_theme/footer-menu.html
sphinx_pythia_theme/footer.html
sphinx_pythia_theme/layout.html
sphinx_pythia_theme/navbar-menu.html
sphinx_pythia_theme/page-banner.html
sphinx_pythia_theme/page-standalone.html
sphinx_pythia_theme/theme.conf
sphinx_pythia_theme/static/sphinx-pythia-theme.min.css
sphinx_pythia_theme/static/sphinx-pythia-theme.min.js
sphinx_pythia_theme-2024.4.0.dist-info/LICENSE
sphinx_pythia_theme-2024.4.0.dist-info/METADATA
sphinx_pythia_theme-2024.4.0.dist-info/WHEEL
sphinx_pythia_theme-2024.4.0.dist-info/entry_points.txt
sphinx_pythia_theme-2024.4.0.dist-info/top_level.txt
sphinx_pythia_theme-2024.4.0.dist-info/zip-safe
sphinx_pythia_theme-2024.4.0.dist-info/RECORD
