Metadata-Version: 2.1
Name: sphinx-pythia-theme
Version: 2024.4.0
Summary: The Sphinx Pythia Theme
Home-page: https://sphinx-pythia-theme.readthedocs.io
Author: Kevin Paul
Author-email: projectpythia@ucar.edu
License: Apache 2.0
Project-URL: Documentation, https://projectpythia.org
Project-URL: Source Code, https://github.com/ProjectPythia/sphinx-pythia-theme
Project-URL: Bug Tracker, https://github.com/ProjectPythia/sphinx-pythia-theme/issues
Keywords: sphinx,theme,jupyter,notebook
Classifier: Development Status :: 3 - Alpha
Classifier: Environment :: Web Environment
Classifier: Intended Audience :: Developers
Classifier: License :: OSI Approved :: Apache Software License
Classifier: Operating System :: OS Independent
Classifier: Programming Language :: Python
Classifier: Programming Language :: Python :: 3
Classifier: Topic :: Internet
Classifier: Topic :: Software Development :: Documentation
License-File: LICENSE
Requires-Dist: sphinx >=5.0
Requires-Dist: sphinx-book-theme >=1.0.0
Requires-Dist: sphinx-design
